Workbook

Sheet EV vs Equity Value
A1: Enterprise Value vs Equity Value
A2: Item | B2: Amount (₹ Cr)
A3: Market Capitalisation | B3: 63051 | E3: Paytm (One97 Communications)
A4: Total Debt | B4: 15
A5: Cash & Cash Equivalents | B5: 12929
A6: Minority Interest | B6: 0
A7: Enterprise Value (EV) | B7: =B3+B4+B6-B5 -> 50137
A8: Equity Value (Market Cap) | B8: =B3 -> 63051
E9: Source: MoneyControl, Screener and Ticker Finology
A10: Interpretation
A11: EV represents the total firm value available to both debt and equity holders.
A12: Equity Value (Market Cap) belongs exclusively to shareholders.
A13: EV is used in M&A, DCF, and EV/EBITDA valuation frameworks.
A14: Paytm is nearly debt-free so EV = Market Cap − Net Cash.

Sheet FCFF Forecast
A1: FCFF Forecast – Free Cash Flow to Firm | Paytm (One97 Communications)
A2: KEY ASSUMPTIONS
A3: Base Revenue FY2025 (₹ Cr) | B3: 7718
A4: Revenue Growth Rate (g) | B4: 0.2
A5: EBIT Margin | B5: 0.08
A6: Tax Rate | B6: 0.25
A7: Depreciation (₹ Cr) | B7: 450
A8: Capital Expenditure (₹ Cr) | B8: 432
A9: Working Capital (₹ Cr) | B9: 200
A11: Year | B11: Revenue (₹ Cr) | C11: EBIT (₹ Cr) | D11: NOPAT (₹ Cr) | E11: Depreciation (₹ Cr) | F11: CapEx (₹ Cr) | G11: WC (₹ Cr) | H11: FCFF (₹ Cr)
A12: FY2026 | B12: =B3*(1+$B$4) -> 9261.6 | C12: =B12*$B$5 -> 740.928 | D12: =C12*(1-$B$6) -> 555.696 | E12: =$B$7 -> 450 | F12: =$B$8 -> 432 | G12: =$B$9 -> 200 | H12: =D12+E12-F12-G12 -> 373.696
A13: FY2027 | B13: =B12*(1+$B$4) -> 11113.92 | C13: =B13*$B$5 -> 889.1136 | D13: =C13*(1-$B$6) -> 666.8352 | E13: =$B$7 -> 450 | F13: =$B$8 -> 432 | G13: =$B$9 -> 200 | H13: =D13+E13-F13-G13 -> 484.8352
A14: FY2028 | B14: =B13*(1+$B$4) -> 13336.704 | C14: =B14*$B$5 -> 1066.9363 | D14: =C14*(1-$B$6) -> 800.20224 | E14: =$B$7 -> 450 | F14: =$B$8 -> 432 | G14: =$B$9 -> 200 | H14: =D14+E14-F14-G14 -> 618.20224
A15: FY2029 | B15: =B14*(1+$B$4) -> 16004.045 | C15: =B15*$B$5 -> 1280.3236 | D15: =C15*(1-$B$6) -> 960.24269 | E15: =$B$7 -> 450 | F15: =$B$8 -> 432 | G15: =$B$9 -> 200 | H15: =D15+E15-F15-G15 -> 778.24269
A16: FY2030 | B16: =B15*(1+$B$4) -> 19204.854 | C16: =B16*$B$5 -> 1536.3883 | D16: =C16*(1-$B$6) -> 1152.2912 | E16: =$B$7 -> 450 | F16: =$B$8 -> 432 | G16: =$B$9 -> 200 | H16: =D16+E16-F16-G16 -> 970.29123

Sheet WACC
A1: WACC – Weighted Average Cost of Capital | Paytm (One97 Communications)
A2: Component | B2: Value
A3: Cost of Equity – Ke | B3: 0.1467
A4: Cost of Debt – Kd | B4: 0.09
A5: Market Value of Equity (₹ Cr) | B5: 63051
A6: Market Value of Debt (₹ Cr) | B6: 15
A7: Tax Rate | B7: 0.25
A9: WACC | B9: =(B5/(B5+B6))*B3+(B6/(B5+B6))*B4*(1-B7) -> 0.14668116
A11: Interpretation
A12: WACC = minimum return required by all capital providers.
A13: Paytm has negligible debt; WACC is almost entirely driven by Cost of Equity.
A14: Beta of -0.66 (negative β) suggests Paytm moves inversely to broader market — unusual for fintech; reflects regulatory disruption period.
A15: WACC is used to discount FCFF in the DCF model .

Sheet Terminal Value
A1: Terminal Value | E1: g
A2: Item | B2: Value
A3: FCFF – Year 5 (FY2030E) (₹ Cr) | B3: ='FCFF Forecast'!H16 -> 970.29123
A4: Growth Rate | B4: 0.04 | E4: Paytm (One97 Communications)
A5: WACC | B5: =WACC!B9 -> 0.14668116
A6: Terminal Value (₹ Cr) | B6: =B3*(1+B4)/(B5-B4) -> 9459.054
A8: Interpretation:
A9: Use of Gordon Growth Model here. The company’s terminal value is estimated at ₹9,459.05 Cr, based on a Year 5 FCFF of ₹970.29 Cr, a 4% perpetual growth rate, and a 14.67% WACC, representing the present value of all future cash flows beyond FY2030.

Sheet Comparable Analysis
A1: Comparable Company Analysis – Indian Fintech Payments Sector
A2: Company | B2: P/E Ratio | C2: EV/EBITDA
A3: Paytm (One97 Comms) | B3: -63.23 | C3: -50.44
A4: SBI Cards | B4: 43.73 | C4: 21.36
A5: MobiKwik | B5: -15.78 | C5: -21.04
A6: Sector Average / Median | B6: =AVERAGE(B3:B5) -> -11.76 | C6: =AVERAGE(C3:C5) -> -16.706667
A8: VALUATION USING COMPARABLE MULTIPLES
A9: Paytm EBITDA (₹ Cr) – FY2026E | B9: -88
A10: Avg EV/EBITDA | B10: 194
A11: Paytm EPS (₹) | B11: -9.44

Sheet Conclusion
A1: Valuation Conclusion – Paytm (One97 Communications Ltd.)
A2: Valuation Method | B2: Value (₹ Cr) | C2: Remarks
A3: Market Cap (Current) | B3: ='EV vs Equity Value'!B3 -> 63051
A4: Enterprise Value (EV) | B4: ='EV vs Equity Value'!B7 -> 50137
A5: DCF – Terminal Value (₹ Cr) | B5: ='Terminal Value'!B6 -> 9459.054
A6: Comparable EV (EV/EBITDA) | B6: ='Comparable Analysis'!C6 -> -16.706667
A8: INVESTMENT DECISION FRAMEWORK
A9: BUY | B9: Intrinsic Value > Market Value | C9: DCF Terminal Value suggests upside if margins improve to 8%
A10: HOLD | B10: Intrinsic Value ≈ Market Value | C10: Current market price =₹987 is near DCF fair value
A11: SELL | B11: Intrinsic Value < Market Value | C11: Risk: regulatory headwinds, UPI fee uncertainty, PhonePe competition
A13: INTERPRETATION
A14: Paytm's intrinsic value (DCF) is sensitive to EBIT margin assumptions. At 8% EBIT margin and 20% revenue CAGR, the company generates positive FCFF by FY2026E.
A15: The EV/EBITDA comparable is of limited use today (all peers are near-breakeven or loss-making), but as the sector matures, this method will gain relevance.
A16: Current market cap of ₹63,051 Cr reflects recovery from 2024 regulatory lows. A HOLD/cautious BUY stance is justified for long-term investors given improving EBITDA trajectory.
A17: UPI incentive reduction, PhonePe market share gain, RBI regulatory scrutiny, and ESOP dilution.
